aind_smartsheet_service_async_client/__init__.py
aind_smartsheet_service_async_client/api_client.py
aind_smartsheet_service_async_client/api_response.py
aind_smartsheet_service_async_client/configuration.py
aind_smartsheet_service_async_client/exceptions.py
aind_smartsheet_service_async_client/py.typed
aind_smartsheet_service_async_client/rest.py
aind_smartsheet_service_async_client/api/__init__.py
aind_smartsheet_service_async_client/api/default_api.py
aind_smartsheet_service_async_client/api/healthcheck_api.py
aind_smartsheet_service_async_client/models/__init__.py
aind_smartsheet_service_async_client/models/funding_model.py
aind_smartsheet_service_async_client/models/health_check.py
aind_smartsheet_service_async_client/models/http_validation_error.py
aind_smartsheet_service_async_client/models/perfusions_model.py
aind_smartsheet_service_async_client/models/protocols_model.py
aind_smartsheet_service_async_client/models/validation_error.py
aind_smartsheet_service_async_client/models/validation_error_loc_inner.py
aind_smartsheet_service_async_client-0.3.1.dist-info/METADATA
aind_smartsheet_service_async_client-0.3.1.dist-info/WHEEL
aind_smartsheet_service_async_client-0.3.1.dist-info/top_level.txt
aind_smartsheet_service_async_client-0.3.1.dist-info/RECORD
